jetback/__init__.py
jetback/django_deploy.py
jetback/fastapi_deploy.py
jetback/flask_deploy.py
jetback-0.1.0.dist-info/LICENSE
jetback-0.1.0.dist-info/METADATA
jetback-0.1.0.dist-info/WHEEL
jetback-0.1.0.dist-info/top_level.txt
jetback-0.1.0.dist-info/RECORD
